docling_haystack/__init__.py
docling_haystack/converter.py
docling_haystack/py.typed
docling_haystack-0.1.1.dist-info/LICENSE
docling_haystack-0.1.1.dist-info/METADATA
docling_haystack-0.1.1.dist-info/WHEEL
docling_haystack-0.1.1.dist-info/RECORD
