Metadata-Version: 2.1
Name: docling-haystack
Version: 0.1.1
Summary: Docling Haystack converter
Author: Panos Vagenas
Author-email: pva@zurich.ibm.com
Requires-Python: >=3.9,<3.13
Classifier: Programming Language :: Python :: 3
Classifier: Programming Language :: Python :: 3.9
Classifier: Programming Language :: Python :: 3.10
Classifier: Programming Language :: Python :: 3.11
Classifier: Programming Language :: Python :: 3.12
Requires-Dist: docling (>=2.9.0,<3.0.0)
Requires-Dist: haystack-ai (>=2.8.0,<3.0.0)
